manifest_loader/__init__.py
manifest_loader/apps.py
manifest_loader/exceptions.py
manifest_loader/loaders.py
manifest_loader/utils.py
manifest_loader/templatetags/__init__.py
manifest_loader/templatetags/manifest.py
tests/__init__.py
tests/test_settings.py
tests/tests.py
django_manifest_loader-1.0.0.dist-info/LICENSE
django_manifest_loader-1.0.0.dist-info/METADATA
django_manifest_loader-1.0.0.dist-info/WHEEL
django_manifest_loader-1.0.0.dist-info/top_level.txt
django_manifest_loader-1.0.0.dist-info/RECORD
