Metadata-Version: 2.1
Name: django-manifest-loader
Version: 1.0.0
Summary: A Django app to load webpack assets.
Home-page: https://www.github.com/shonin/django-manifest-loader
Author: Shonin
Author-email: emc@hey.com
License: BSD-3-Clause
Keywords: django,webpack,manifest,loader
Platform: UNKNOWN
Classifier: Environment :: Web Environment
Classifier: Framework :: Django
Classifier: Framework :: Django :: 3.1
Classifier: Intended Audience :: Developers
Classifier: License :: OSI Approved :: BSD License
Classifier: Operating System :: OS Independent
Classifier: Programming Language :: Python
Classifier: Programming Language :: Python :: 3
Classifier: Programming Language :: Python :: 3 :: Only
Classifier: Programming Language :: Python :: 3.6
Classifier: Programming Language :: Python :: 3.7
Classifier: Programming Language :: Python :: 3.8
Classifier: Topic :: Internet :: WWW/HTTP
Classifier: Topic :: Internet :: WWW/HTTP :: Dynamic Content
